LICENSE.txt
MANIFEST.in
README.md
requirements.txt
setup.py
django_user_map.egg-info/PKG-INFO
django_user_map.egg-info/SOURCES.txt
django_user_map.egg-info/dependency_links.txt
django_user_map.egg-info/not-zip-safe
django_user_map.egg-info/requires.txt
django_user_map.egg-info/top_level.txt
user_map/__init__.py
user_map/admin.py
user_map/app_settings.py
user_map/run_tests.py
user_map/serializers.py
user_map/urls.py
user_map/views.py
user_map/forms/__init__.py
user_map/forms/custom_widget.py
user_map/forms/user.py
user_map/management/__init__.py
user_map/management/commands/__init__.py
user_map/management/commands/update_roles.py
user_map/migrations/0001_initial.py
user_map/migrations/0002_populate_roles.py
user_map/migrations/0003_usermap_website.py
user_map/migrations/__init__.py
user_map/models/__init__.py
user_map/models/role.py
user_map/models/user.py
user_map/static/user_map/css/MarkerCluster.css
user_map/static/user_map/css/MarkerCluster.user-map.css
user_map/static/user_map/css/MarkerCluster.user-map.ie.css
user_map/static/user_map/css/bootstrap.css
user_map/static/user_map/css/user-map.css
user_map/static/user_map/css/wrap-bootstrap.css
user_map/static/user_map/css/wrap-bootstrap.less
user_map/static/user_map/css/images/layers-2x.png
user_map/static/user_map/css/images/layers.png
user_map/static/user_map/fonts/glyphicons-halflings-regular.eot
user_map/static/user_map/fonts/glyphicons-halflings-regular.svg
user_map/static/user_map/fonts/glyphicons-halflings-regular.ttf
user_map/static/user_map/fonts/glyphicons-halflings-regular.woff
user_map/static/user_map/img/badge-developer.png
user_map/static/user_map/img/badge-trainer.png
user_map/static/user_map/img/badge-user.png
user_map/static/user_map/img/logo.png
user_map/static/user_map/img/shadow-icon.png
user_map/static/user_map/img/user-icon.png
user_map/static/user_map/js/bootstrap.min.js
user_map/static/user_map/js/jquery.js
user_map/static/user_map/js/jsrender.min.js
user_map/static/user_map/js/leaflet.markercluster-src.js
user_map/static/user_map/js/user-map.js
user_map/static/user_map/js/validate.js
user_map/static/user_map/js/images/marker-icon.png
user_map/static/user_map/js/images/marker-shadow.png
