Metadata-Version: 1.0
Name: django-user-map
Version: 1.1.1
Summary: A simple app for creating a community user map in your django web site.
Home-page: http://pypi.python.org/pypi/django-user-map/
Author: Akbar Gumbira
Author-email: akbargumbira@gmail.com
License: LICENSE.txt
Platform: UNKNOWN
